infiray_lrf/__init__.py
infiray_lrf/commands.py
infiray_lrf/logger.py
infiray_lrf/sender.py
infiray_lrf-1.0.1.dist-info/LICENSE
infiray_lrf-1.0.1.dist-info/METADATA
infiray_lrf-1.0.1.dist-info/WHEEL
infiray_lrf-1.0.1.dist-info/entry_points.txt
infiray_lrf-1.0.1.dist-info/top_level.txt
infiray_lrf-1.0.1.dist-info/RECORD
