Metadata-Version: 2.1
Name: infiray-lrf
Version: 1.0.1
Summary: Command sender for the InfiRay LR2000 / LR3000 Long Range Finder
Author-email: o-murphy <thehelixpg@gmail.com>
License: GNU LESSER GENERAL PUBLIC LICENSE
Project-URL: Homepage, https://github.com/o-murphy/infiray-lrf
Project-URL: Bug Reports, https://github.com/o-murphy/infiray-lrf/issues
Project-URL: Source, https://github.com/o-murphy/infiray-lrf
Keywords: pyserial,infiray,iray,lrf,serial,long range finder,python,python3
Classifier: Intended Audience :: Developers
Classifier: Natural Language :: English
Classifier: Programming Language :: Python
Classifier: Topic :: Software Development :: Libraries :: Python Modules
Classifier: Programming Language :: Python :: 3
Classifier: Programming Language :: Python :: 3 :: Only
Classifier: Programming Language :: Python :: 3.9
Classifier: Programming Language :: Python :: 3.10
Classifier: Programming Language :: Python :: 3.11
Classifier: Programming Language :: Python :: 3.12
Classifier: Operating System :: OS Independent
Classifier: Programming Language :: Python :: Implementation :: CPython
Requires-Python: >=3.9
License-File: LICENSE
Requires-Dist: pyserial
Requires-Dist: construct
Provides-Extra: dev
Requires-Dist: build ; extra == 'dev'
